pymudata/__init__.py
pymudata/activity.py
pymudata/dataset.py
pymudata/utils.py
pymudata-0.0.1.dist-info/LICENSE
pymudata-0.0.1.dist-info/METADATA
pymudata-0.0.1.dist-info/WHEEL
pymudata-0.0.1.dist-info/top_level.txt
pymudata-0.0.1.dist-info/RECORD
