Metadata-Version: 2.1
Name: pymudata
Version: 0.0.1
Summary: Wrapepr for inertial signal datasets
Home-page: UNKNOWN
Author: Antonio Bevilacqua
Author-email: b3by.in.th3.sky@gmail.com
Maintainer: Antonio Bevilacqua
Maintainer-email: b3by.in.th3.sky@gmail.com
License: UNKNOWN
Download-URL: https://github.com/b3by/pymudata/archive/v0.0.1.tar.gz
Platform: UNKNOWN
Classifier: Intended Audience :: Developers
Classifier: Topic :: Software Development :: Build Tools
Classifier: License :: OSI Approved :: MIT License
Classifier: Programming Language :: Python :: 3.7
Requires-Dist: numpy
Requires-Dist: pandas
